odoo/addons/account_promissory_note_bankia/README.rst
odoo/addons/account_promissory_note_bankia/__init__.py
odoo/addons/account_promissory_note_bankia/__manifest__.py
odoo/addons/account_promissory_note_bankia/data/account_promissory_note_report_data.xml
odoo/addons/account_promissory_note_bankia/i18n/account_promissory_note_bankia.pot
odoo/addons/account_promissory_note_bankia/i18n/ca.po
odoo/addons/account_promissory_note_bankia/i18n/es.po
odoo/addons/account_promissory_note_bankia/readme/CONFIGURE.rst
odoo/addons/account_promissory_note_bankia/readme/CONTRIBUTORS.rst
odoo/addons/account_promissory_note_bankia/readme/DESCRIPTION.rst
odoo/addons/account_promissory_note_bankia/readme/USAGE.rst
odoo/addons/account_promissory_note_bankia/report/__init__.py
odoo/addons/account_promissory_note_bankia/report/account_promissory_note_writing_report.xml
odoo/addons/account_promissory_note_bankia/report/check_print.py
odoo/addons/account_promissory_note_bankia/static/description/icon.png
odoo/addons/account_promissory_note_bankia/static/description/index.html
odoo/addons/account_promissory_note_bankia/views/report_promissory_note.xml
odoo12_addon_account_promissory_note_bankia-12.0.1.0.0.99.dev6.dist-info/METADATA
odoo12_addon_account_promissory_note_bankia-12.0.1.0.0.99.dev6.dist-info/WHEEL
odoo12_addon_account_promissory_note_bankia-12.0.1.0.0.99.dev6.dist-info/top_level.txt
odoo12_addon_account_promissory_note_bankia-12.0.1.0.0.99.dev6.dist-info/RECORD
